{
	"status_code": 200,
	"message": "OK",
	"data": {
		"id": "01954354-31b0-73d4-b35c-7456c69ae877",
		"service_cost": "100000",
		"service_start_date": "2025-03-01",
		"service_end_date": "2025-03-07",
		"service_start_time": "02:53:59",
		"service_end_time": "05:56:59",
		"service_time_time_zone": "Asia/Tokyo",
		"has_pending_negotiation": false,
		"created_at": "2025-02-27T01:35:46.096254+08:00",
		"service": { "id": "01945f56-5651-7459-bab4-8d5f3438ce70", "name": "Service mesin AC" },
		"service_provider": {
			"id": "01945f56-5651-7459-bab4-8d5f3438ce70",
			"name": "ARIS ",
			"logo_url": "https://kelarin.s3.ap-southeast-3.amazonaws.com/service_provider/logo/1736766273_2f3ab033a43e444ce371694c282ae76e2df87a53?X-Amz-Algorithm=AWS4-HMAC-SHA256\u0026X-Amz-Credential=AKIA3FLD3HOKAU2EI7UU%2F20250228%2Fap-southeast-3%2Fs3%2Faws4_request\u0026X-Amz-Date=20250228T082124Z\u0026X-Amz-Expires=900\u0026X-Amz-SignedHeaders=host\u0026x-id=GetObject\u0026X-Amz-Signature=83365deb7ec416727e40d1b4e12eba17ade1928f5e966593fa1c9ce0cc425cb8",
			"received_rating_count": 0,
			"received_rating_average": 0
		},
		"address": {
			"id": "019541b4-1bfc-75fb-b38c-9474aecf4400",
			"name": "Office 1",
			"province": "Jawa Barat",
			"city": "Bekasi",
			"lat": -6.240250010485369,
			"lng": 107.02349271771118,
			"address": "ajwdna kwndkj awkd"
		}
	}
}
